<annotation>
	<folder>fotos</folder>
	<filename>IMG_20220603_131211081.jpg</filename>
	<path>C:\FACULTAD\ORGANIZACION DE DATOS\fotos\IMG_20220603_131211081.jpg</path>
	<source>
		<database>Unknown</database>
	</source>
	<size>
		<width>1197</width>
		<height>1600</height>
		<depth>3</depth>
	</size>
	<segmented>0</segmented>
	<object>
		<name>cartera</name>
		<pose>Unspecified</pose>
		<truncated>0</truncated>
		<difficult>0</difficult>
		<bndbox>
			<xmin>82</xmin>
			<ymin>251</ymin>
			<xmax>1094</xmax>
			<ymax>1436</ymax>
		</bndbox>
	</object>
	<object>
		<name>tela</name>
		<pose>Unspecified</pose>
		<truncated>0</truncated>
		<difficult>0</difficult>
		<bndbox>
			<xmin>133</xmin>
			<ymin>665</ymin>
			<xmax>1072</xmax>
			<ymax>1416</ymax>
		</bndbox>
	</object>
</annotation>
