<annotation>
	<folder>carteras</folder>
	<filename>tjshiao-07.jpg</filename>
	<path>images/carteras/tjshiao-07.jpg</path>
	<source>
		<database>Unknown</database>
	</source>
	<size>
		<width>225</width>
		<height>225</height>
		<depth>3</depth>
	</size>
	<segmented>0</segmented>
	<object>
		<name>cartera</name>
		<pose>Unspecified</pose>
		<truncated>0</truncated>
		<difficult>0</difficult>
		<bndbox>
			<xmin>21</xmin>
			<ymin>6</ymin>
			<xmax>202</xmax>
			<ymax>209</ymax>
		</bndbox>
	</object>
	<object>
		<name>cuero</name>
		<pose>Unspecified</pose>
		<truncated>0</truncated>
		<difficult>0</difficult>
		<bndbox>
			<xmin>48</xmin>
			<ymin>121</ymin>
			<xmax>165</xmax>
			<ymax>181</ymax>
		</bndbox>
	</object>
</annotation>
